uapp/__init__.py
uapp/main.py
uapp/lib/__init__.py
uapp/lib/args.py
uapp/lib/utils.py
uapp-1.2.3.data/scripts/uapp
uapp-1.2.3.dist-info/LICENSE
uapp-1.2.3.dist-info/METADATA
uapp-1.2.3.dist-info/WHEEL
uapp-1.2.3.dist-info/top_level.txt
uapp-1.2.3.dist-info/RECORD
