Metadata-Version: 2.1
Name: uapp
Version: 1.2.3
Summary: This program tries to update all installed packages through pip.
Home-page: https://github.com/accessmaker/UAPP
Download-URL: https://github.com/accessmaker/UAPP.git
Author: Lucas dSilva
Author-email: accessmaker.mlbb@gmail.com
License: MIT
Keywords: uapp,pip,update
Classifier: Development Status :: 5 - Production/Stable
License-File: LICENSE
Requires-Dist: colorama
